calculator.py
simple_calculator_u_aaa-0.0.3.dist-info/LICENSE
simple_calculator_u_aaa-0.0.3.dist-info/METADATA
simple_calculator_u_aaa-0.0.3.dist-info/WHEEL
simple_calculator_u_aaa-0.0.3.dist-info/top_level.txt
simple_calculator_u_aaa-0.0.3.dist-info/RECORD
