Metadata-Version: 2.1
Name: simple-calculator-u-aaa
Version: 0.0.3
Summary: A small calculator package
Home-page: https://github.com/u-aaa/simple_calculator
Author: Blessing Philips
Author-email: blessingphilips@ymail.com
License: UNKNOWN
Project-URL: Bug Tracker, https://github.com/u-aaa/simple_calculator/issues
Platform: UNKNOWN
Classifier: Programming Language :: Python :: 3
Classifier: License :: OSI Approved :: MIT License
Classifier: Operating System :: OS Independent
Requires-Python: >=3.6
License-File: LICENSE
